Ferrum/__init__.py
ferrum-0.1.dist-info/licenses/LICENSE
ferrum-0.1.dist-info/METADATA
ferrum-0.1.dist-info/WHEEL
ferrum-0.1.dist-info/top_level.txt
ferrum-0.1.dist-info/RECORD
