Metadata-Version: 2.4
Name: Ferrum
Version: 0.1
Summary: Easy to use project package manager
Home-page: https://github.com/literal-gargoyle/Francium
Author: David Ikeda
Author-email: dev.literalgargoyle@gmail.com
License: MIT
Classifier: Development Status :: 3 - Alpha
Classifier: Intended Audience :: Developers
Classifier: Programming Language :: Python :: 3
Classifier: Operating System :: Unix
License-File: LICENSE
Dynamic: author
Dynamic: author-email
Dynamic: classifier
Dynamic: description
Dynamic: description-content-type
Dynamic: home-page
Dynamic: license
Dynamic: license-file
Dynamic: summary
